pip_custom_platform/__init__.py
pip_custom_platform/_main.py
pip_custom_platform/default_platform.py
pip_custom_platform/main.py
pip_custom_platform/pymonkey.py
pip_custom_platform-0.5.0.dist-info/LICENSE
pip_custom_platform-0.5.0.dist-info/METADATA
pip_custom_platform-0.5.0.dist-info/WHEEL
pip_custom_platform-0.5.0.dist-info/entry_points.txt
pip_custom_platform-0.5.0.dist-info/top_level.txt
pip_custom_platform-0.5.0.dist-info/RECORD
